CHANGES.txt
LICENSE.txt
MANIFEST.in
README.txt
setup.cfg
setup.py
bdt/__init__.py
bdt/__main__.py
bdt/sitemap.py
bdt_sitemap.egg-info/PKG-INFO
bdt_sitemap.egg-info/SOURCES.txt
bdt_sitemap.egg-info/dependency_links.txt
bdt_sitemap.egg-info/entry_points.txt
bdt_sitemap.egg-info/requires.txt
bdt_sitemap.egg-info/top_level.txt